osn_selenium/__init__.py
osn_selenium/_base_models.py
osn_selenium/_cdp_import.py
osn_selenium/_functions.py
osn_selenium/_typehints.py
osn_selenium/base_mixin.py
osn_selenium/models.py
osn_selenium/trio_threads_mixin.py
osn_selenium/abstract/__init__.py
osn_selenium/abstract/executors/__init__.py
osn_selenium/abstract/executors/cdp.py
osn_selenium/abstract/executors/javascript.py
osn_selenium/abstract/executors/cdp/__init__.py
osn_selenium/abstract/executors/cdp/accessibility.py
osn_selenium/abstract/executors/cdp/animation.py
osn_selenium/abstract/executors/cdp/audits.py
osn_selenium/abstract/executors/cdp/autofill.py
osn_selenium/abstract/executors/cdp/background_service.py
osn_selenium/abstract/executors/cdp/bluetooth_emulation.py
osn_selenium/abstract/executors/cdp/browser.py
osn_selenium/abstract/executors/cdp/cache_storage.py
osn_selenium/abstract/executors/cdp/cast.py
osn_selenium/abstract/executors/cdp/console.py
osn_selenium/abstract/executors/cdp/css.py
osn_selenium/abstract/executors/cdp/debugger.py
osn_selenium/abstract/executors/cdp/device_access.py
osn_selenium/abstract/executors/cdp/device_orientation.py
osn_selenium/abstract/executors/cdp/dom.py
osn_selenium/abstract/executors/cdp/dom_debugger.py
osn_selenium/abstract/executors/cdp/dom_snapshot.py
osn_selenium/abstract/executors/cdp/dom_storage.py
osn_selenium/abstract/executors/cdp/emulation.py
osn_selenium/abstract/executors/cdp/event_breakpoints.py
osn_selenium/abstract/executors/cdp/extensions.py
osn_selenium/abstract/executors/cdp/fed_cm.py
osn_selenium/abstract/executors/cdp/fetch.py
osn_selenium/abstract/executors/cdp/file_system.py
osn_selenium/abstract/executors/cdp/headless_experimental.py
osn_selenium/abstract/executors/cdp/heap_profiler.py
osn_selenium/abstract/executors/cdp/indexed_db.py
osn_selenium/abstract/executors/cdp/input.py
osn_selenium/abstract/executors/cdp/inspector.py
osn_selenium/abstract/executors/cdp/io.py
osn_selenium/abstract/executors/cdp/layer_tree.py
osn_selenium-1.1.0.dist-info/METADATA
osn_selenium-1.1.0.dist-info/WHEEL
osn_selenium-1.1.0.dist-info/top_level.txt
osn_selenium-1.1.0.dist-info/RECORD
