Metadata-Version: 2.4
Name: osn-selenium
Version: 1.1.0
Summary: An advanced, asynchronous wrapper for Selenium designed for fine-grained browser control. It leverages `trio` for async operations, provides human-like action chains for more natural automation, and offers deep integration with the Chrome DevTools Protocol (CDP) for advanced features like network interception. The library is structured to be extensible, with built-in support for Blink-based browsers like Chrome, Edge, and Yandex.
Author-email: oddshellnick <oddshellnick.programming@gmail.com>
Project-URL: Homepage, https://github.com/oddshellnick/osn-selenium
Project-URL: Issues, https://github.com/oddshellnick/osn-selenium/issues
Requires-Python: >=3.12
Requires-Dist: trio<1.0.0,>=0.32.0
Requires-Dist: selenium<5.0.0,>=4.40.0
Requires-Dist: pydantic<3.0.0,>=2.0.0
Requires-Dist: trio-websocket<1.0.0,>=0.12.0
Requires-Dist: pywin32>=310; sys_platform == "win32"
Requires-Dist: osn-system-utils<0.1.0,>=0.0.4
